firebase_utils/__init__.py
firebase_utils/singleton.py
singleton_firebase-0.0.2.dist-info/LICENCE
singleton_firebase-0.0.2.dist-info/METADATA
singleton_firebase-0.0.2.dist-info/WHEEL
singleton_firebase-0.0.2.dist-info/top_level.txt
singleton_firebase-0.0.2.dist-info/RECORD
