Metadata-Version: 2.1
Name: singleton-firebase
Version: 0.0.2
Summary: A Singleton factory to firebase
Home-page: https://bitbucket.org/cargamos/firebase
Author: Moisés Rangel
Author-email: moises.rangel@gmail.com
License: UNKNOWN
Platform: UNKNOWN
Classifier: Programming Language :: Python :: 3
Classifier: License :: OSI Approved :: MIT License
Classifier: Operating System :: OS Independent
